<?xml version="1.0" encoding="UTF-8"?>
<!DOCTYPE MAN SYSTEM "../../../../../../../man/manrev.dtd">
<MAN>
  <LANGUAGE>eng</LANGUAGE>

  <TITLE>FLEX_DMB_buzzer</TITLE>

  <TYPE>Scicos block</TYPE>

  <DATE>October 2011</DATE>

  <SHORT_DESCRIPTION name="FLEX_DMB_buzzer">palette: FLEX-DemoBoard</SHORT_DESCRIPTION>

  <DESCRIPTION>
    <P><IMG src="FLEX_DMB_buzzer.gif"></IMG></P>
    <P><VERB>palette: FLEX-DemoBoard</VERB></P>
    <P>This block controls the buzzer mounted on the Demo Daughter Board. 
       The input value is the frequency of the buzzer sound, in Hz.</P>
  </DESCRIPTION>
  
  <SEE_ALSO>
    <SEE_ALSO_ITEM>
      <LINK> FLEX_DMB_adcin </LINK>
    </SEE_ALSO_ITEM>

    <SEE_ALSO_ITEM>
      <LINK> FLEX_DMB_button </LINK>
    </SEE_ALSO_ITEM>

    <SEE_ALSO_ITEM>
      <LINK> FLEX_DMB_ldr </LINK>
    </SEE_ALSO_ITEM>

    <SEE_ALSO_ITEM>
      <LINK> FLEX_DMB_lcd </LINK>
    </SEE_ALSO_ITEM>

    <SEE_ALSO_ITEM>
      <LINK> FLEX_DMB_lbarrier </LINK>
    </SEE_ALSO_ITEM>

    <SEE_ALSO_ITEM>
      <LINK> FLEX_DMB_gpout </LINK>
    </SEE_ALSO_ITEM>

    <SEE_ALSO_ITEM>
      <LINK> FLEX_DMB_gpin </LINK>
    </SEE_ALSO_ITEM>

    <SEE_ALSO_ITEM>
      <LINK> FLEX_DMB_encoder </LINK>
    </SEE_ALSO_ITEM>

    <SEE_ALSO_ITEM>
      <LINK> FLEX_DMB_dac </LINK>
    </SEE_ALSO_ITEM>

    <SEE_ALSO_ITEM>
      <LINK> FLEX_DMB_acc </LINK>
    </SEE_ALSO_ITEM>

    <SEE_ALSO_ITEM>
      <LINK>FLEX_DMB_trim</LINK>
    </SEE_ALSO_ITEM>

    <SEE_ALSO_ITEM>
      <LINK>FLEX_DMB_therm</LINK>
    </SEE_ALSO_ITEM>

    <SEE_ALSO_ITEM>
      <LINK>FLEX_DMB_pwm</LINK>
    </SEE_ALSO_ITEM>

    <SEE_ALSO_ITEM>
      <LINK>FLEX_DMB_leds</LINK>
    </SEE_ALSO_ITEM>
  </SEE_ALSO>

  <AUTHOR>Dario Di Stefano, Evidence Srl, 2011</AUTHOR>
</MAN>